arabic_pronounce/__init__.py
arabic_pronounce-0.2.5.dist-info/METADATA
arabic_pronounce-0.2.5.dist-info/RECORD
arabic_pronounce-0.2.5.dist-info/WHEEL
arabic_pronounce-0.2.5.dist-info/top_level.txt
